{"remainingRequest":"C:\\Users\\kaiki\\Documents\\NetBeansProjects\\concesionario\\node_modules\\thread-loader\\dist\\cjs.js??ref--4-2!C:\\Users\\kaiki\\Documents\\NetBeansProjects\\concesionario\\node_modules\\ts-loader\\index.js??ref--4-3!C:\\Users\\kaiki\\Documents\\NetBeansProjects\\concesionario\\node_modules\\tslint-loader\\index.js!C:\\Users\\kaiki\\Documents\\NetBeansProjects\\concesionario\\src\\main\\webapp\\app\\entities\\marca\\marca.tsx","dependencies":[{"path":"C:\\Users\\kaiki\\Documents\\NetBeansProjects\\concesionario\\src\\main\\webapp\\app\\entities\\marca\\marca.tsx","mtime":1660603227230},{"path":"C:\\Users\\kaiki\\Documents\\NetBeansProjects\\concesionario\\node_modules\\react-hot-loader\\webpack.js","mtime":1505850161000},{"path":"C:\\Users\\kaiki\\Documents\\NetBeansProjects\\concesionario\\node_modules\\cache-loader\\dist\\cjs.js","mtime":0},{"path":"C:\\Users\\kaiki\\Documents\\NetBeansProjects\\concesionario\\node_modules\\thread-loader\\dist\\cjs.js","mtime":499162500000},{"path":"C:\\Users\\kaiki\\Documents\\NetBeansProjects\\concesionario\\node_modules\\ts-loader\\index.js","mtime":499162500000},{"path":"C:\\Users\\kaiki\\Documents\\NetBeansProjects\\concesionario\\node_modules\\tslint-loader\\index.js","mtime":1519899048000}],"contextDependencies":[],"result":["import * as tslib_1 from \"tslib\";\r\nimport React from 'react';\r\nimport { connect } from 'react-redux';\r\nimport { Link } from 'react-router-dom';\r\nimport { Button, Table } from 'reactstrap';\r\n// tslint:disable-next-line:no-unused-variable\r\nimport { Translate } from 'react-jhipster';\r\nimport { FontAwesomeIcon } from '@fortawesome/react-fontawesome';\r\nimport { getEntities } from './marca.reducer';\r\nvar Marca = /** @class */ (function (_super) {\r\n    tslib_1.__extends(Marca, _super);\r\n    function Marca() {\r\n        return _super !== null && _super.apply(this, arguments) || this;\r\n    }\r\n    Marca.prototype.componentDidMount = function () {\r\n        this.props.getEntities();\r\n    };\r\n    Marca.prototype.render = function () {\r\n        var _a = this.props, marcaList = _a.marcaList, match = _a.match;\r\n        return (React.createElement(\"div\", null,\r\n            React.createElement(\"h2\", { id: \"marca-heading\" },\r\n                React.createElement(Translate, { contentKey: \"concesionarioApp.marca.home.title\" }, \"Marcas\"),\r\n                React.createElement(Link, { to: match.url + \"/new\", className: \"btn btn-primary float-right jh-create-entity\", id: \"jh-create-entity\" },\r\n                    React.createElement(FontAwesomeIcon, { icon: \"plus\" }),\r\n                    \"\\u00A0\",\r\n                    React.createElement(Translate, { contentKey: \"concesionarioApp.marca.home.createLabel\" }, \"Create new Marca\"))),\r\n            React.createElement(\"div\", { className: \"table-responsive\" },\r\n                React.createElement(Table, { responsive: true },\r\n                    React.createElement(\"thead\", null,\r\n                        React.createElement(\"tr\", null,\r\n                            React.createElement(\"th\", null,\r\n                                React.createElement(Translate, { contentKey: \"global.field.id\" }, \"ID\")),\r\n                            React.createElement(\"th\", null,\r\n                                React.createElement(Translate, { contentKey: \"concesionarioApp.marca.Nombre\" }, \"Nombre\")),\r\n                            React.createElement(\"th\", null,\r\n                                React.createElement(Translate, { contentKey: \"concesionarioApp.marca.Pais\" }, \"Pais\")),\r\n                            React.createElement(\"th\", null))),\r\n                    React.createElement(\"tbody\", null, marcaList.map(function (marca, i) { return (React.createElement(\"tr\", { key: \"entity-\" + i },\r\n                        React.createElement(\"td\", null,\r\n                            React.createElement(Button, { tag: Link, to: match.url + \"/\" + marca.id, color: \"link\", size: \"sm\" }, marca.id)),\r\n                        React.createElement(\"td\", null, marca.Nombre),\r\n                        React.createElement(\"td\", null, marca.Pais),\r\n                        React.createElement(\"td\", { className: \"text-right\" },\r\n                            React.createElement(\"div\", { className: \"btn-group flex-btn-group-container\" },\r\n                                React.createElement(Button, { tag: Link, to: match.url + \"/\" + marca.id, color: \"info\", size: \"sm\" },\r\n                                    React.createElement(FontAwesomeIcon, { icon: \"eye\" }),\r\n                                    \" \",\r\n                                    React.createElement(\"span\", { className: \"d-none d-md-inline\" },\r\n                                        React.createElement(Translate, { contentKey: \"entity.action.view\" }, \"View\"))),\r\n                                React.createElement(Button, { tag: Link, to: match.url + \"/\" + marca.id + \"/edit\", color: \"primary\", size: \"sm\" },\r\n                                    React.createElement(FontAwesomeIcon, { icon: \"pencil-alt\" }),\r\n                                    \" \",\r\n                                    React.createElement(\"span\", { className: \"d-none d-md-inline\" },\r\n                                        React.createElement(Translate, { contentKey: \"entity.action.edit\" }, \"Edit\"))),\r\n                                React.createElement(Button, { tag: Link, to: match.url + \"/\" + marca.id + \"/delete\", color: \"danger\", size: \"sm\" },\r\n                                    React.createElement(FontAwesomeIcon, { icon: \"trash\" }),\r\n                                    \" \",\r\n                                    React.createElement(\"span\", { className: \"d-none d-md-inline\" },\r\n                                        React.createElement(Translate, { contentKey: \"entity.action.delete\" }, \"Delete\"))))))); }))))));\r\n    };\r\n    return Marca;\r\n}(React.Component));\r\nexport { Marca };\r\nvar mapStateToProps = function (_a) {\r\n    var marca = _a.marca;\r\n    return ({\r\n        marcaList: marca.entities,\r\n    });\r\n};\r\nvar mapDispatchToProps = {\r\n    getEntities: getEntities,\r\n};\r\nexport default connect(mapStateToProps, mapDispatchToProps)(Marca);\r\n",{"version":3,"file":"C:\\Users\\kaiki\\Documents\\NetBeansProjects\\concesionario\\src\\main\\webapp\\app\\entities\\marca\\marca.tsx","sourceRoot":"","sources":["C:\\Users\\kaiki\\Documents\\NetBeansProjects\\concesionario\\node_modules\\tslint-loader\\index.js!C:\\Users\\kaiki\\Documents\\NetBeansProjects\\concesionario\\src\\main\\webapp\\app\\entities\\marca\\marca.tsx"],"names":[],"mappings":";AAAA,OAAO,KAAK,MAAM,OAAO,CAAC;AAC1B,OAAO,EAAE,OAAO,EAAE,MAAM,aAAa,CAAC;AACtC,OAAO,EAAE,IAAI,EAAuB,MAAM,kBAAkB,CAAC;AAC7D,OAAO,EAAE,MAAM,EAAY,KAAK,EAAE,MAAM,YAAY,CAAC;AACrD,8CAA8C;AAC9C,OAAO,EACL,SAAS,EAEV,MAAM,gBAAgB,CAAC;AACxB,OAAO,EAAE,eAAe,EAAE,MAAM,gCAAgC,CAAC;AAGjE,OAAO,EACL,WAAW,EACZ,MAAM,iBAAiB,CAAC;AAQzB;IAA2B,iCAA4B;IAAvD;;IAsEA,CAAC;IApEC,iCAAiB,GAAjB;QACE,IAAI,CAAC,KAAK,CAAC,WAAW,EAAE,CAAC;IAC3B,CAAC;IAMD,sBAAM,GAAN;QACQ,IAAA,eAAgC,EAA9B,wBAAS,EAAE,gBAAK,CAAe;QACvC,OAAO,CACL;YACE,4BAAI,EAAE,EAAC,eAAe;gBACpB,oBAAC,SAAS,IAAC,UAAU,EAAC,mCAAmC,aAAmB;gBAC5E,oBAAC,IAAI,IAAC,EAAE,EAAK,KAAK,CAAC,GAAG,SAAM,EAAE,SAAS,EAAC,8CAA8C,EAAC,EAAE,EAAC,kBAAkB;oBAC1G,oBAAC,eAAe,IAAC,IAAI,EAAC,MAAM,GAAG;;oBAC/B,oBAAC,SAAS,IAAC,UAAU,EAAC,yCAAyC,uBAEnD,CACP,CACJ;YACL,6BAAK,SAAS,EAAC,kBAAkB;gBAC/B,oBAAC,KAAK,IAAC,UAAU;oBACf;wBACE;4BACE;gCAAI,oBAAC,SAAS,IAAC,UAAU,EAAC,iBAAiB,SAAe,CAAK;4BAC/D;gCAAI,oBAAC,SAAS,IAAC,UAAU,EAAC,+BAA+B,aAAmB,CAAK;4BACjF;gCAAI,oBAAC,SAAS,IAAC,UAAU,EAAC,6BAA6B,WAAiB,CAAK;4BAC7E,+BAAM,CACH,CACC;oBACR,mCAEI,SAAS,CAAC,GAAG,CAAC,UAAC,KAAK,EAAE,CAAC,IAAK,OAAA,CAC5B,4BAAI,GAAG,EAAE,YAAU,CAAG;wBACpB;4BACE,oBAAC,MAAM,IAAC,GAAG,EAAE,IAAI,EAAE,EAAE,EAAK,KAAK,CAAC,GAAG,SAAI,KAAK,CAAC,EAAI,EAAE,KAAK,EAAC,MAAM,EAAC,IAAI,EAAC,IAAI,IACtE,KAAK,CAAC,EAAE,CACF,CACN;wBACL,gCACG,KAAK,CAAC,MAAM,CACV;wBACL,gCACG,KAAK,CAAC,IAAI,CACR;wBACH,4BAAI,SAAS,EAAC,YAAY;4BACxB,6BAAK,SAAS,EAAC,oCAAoC;gCACjD,oBAAC,MAAM,IAAC,GAAG,EAAE,IAAI,EAAE,EAAE,EAAK,KAAK,CAAC,GAAG,SAAI,KAAK,CAAC,EAAI,EAAE,KAAK,EAAC,MAAM,EAAC,IAAI,EAAC,IAAI;oCACvE,oBAAC,eAAe,IAAC,IAAI,EAAC,KAAK,GAAG;;oCAAC,8BAAM,SAAS,EAAC,oBAAoB;wCAAE,oBAAC,SAAS,IAAC,UAAU,EAAC,oBAAoB,WAAiB,CAAO,CAChI;gCACT,oBAAC,MAAM,IAAC,GAAG,EAAE,IAAI,EAAE,EAAE,EAAK,KAAK,CAAC,GAAG,SAAI,KAAK,CAAC,EAAE,UAAO,EAAE,KAAK,EAAC,SAAS,EAAC,IAAI,EAAC,IAAI;oCAC/E,oBAAC,eAAe,IAAC,IAAI,EAAC,YAAY,GAAG;;oCAAC,8BAAM,SAAS,EAAC,oBAAoB;wCAAC,oBAAC,SAAS,IAAC,UAAU,EAAC,oBAAoB,WAAiB,CAAO,CACtI;gCACT,oBAAC,MAAM,IAAC,GAAG,EAAE,IAAI,EAAE,EAAE,EAAK,KAAK,CAAC,GAAG,SAAI,KAAK,CAAC,EAAE,YAAS,EAAE,KAAK,EAAC,QAAQ,EAAC,IAAI,EAAC,IAAI;oCAChF,oBAAC,eAAe,IAAC,IAAI,EAAC,OAAO,GAAG;;oCAAC,8BAAM,SAAS,EAAC,oBAAoB;wCAAC,oBAAC,SAAS,IAAC,UAAU,EAAC,sBAAsB,aAAmB,CAAO,CACrI,CACL,CACH,CACF,CACN,EA3B2B,CA2B3B,CAAC,CAEE,CACF,CACJ,CACF,CACP,CAAC;IACJ,CAAC;IACH,YAAC;AAAD,CAAC,AAtED,CAA2B,KAAK,CAAC,SAAS,GAsEzC;;AAED,IAAM,eAAe,GAAG,UAAC,EAAqB;QAAnB,gBAAK;IAAmB,OAAA,CAAC;QAClD,SAAS,EAAE,KAAK,CAAC,QAAQ;KAC1B,CAAC;AAFiD,CAEjD,CAAC;AAEH,IAAM,kBAAkB,GAAG;IAC1B,WAAW,aAAA;CACX,CAAC;AAKF,eAAe,OAAO,CAAC,eAAe,EAAE,kBAAkB,CAAC,CAAC,KAAK,CAAC,CAAC","sourcesContent":["import React from 'react';\nimport { connect } from 'react-redux';\nimport { Link, RouteComponentProps } from 'react-router-dom';\nimport { Button, Col, Row, Table } from 'reactstrap';\n// tslint:disable-next-line:no-unused-variable\nimport {\n  Translate,\n  ICrudGetAllAction\n} from 'react-jhipster';\nimport { FontAwesomeIcon } from '@fortawesome/react-fontawesome';\n\nimport { IRootState } from 'app/shared/reducers';\nimport {\n  getEntities\n} from './marca.reducer';\nimport { IMarca } from 'app/shared/model/marca.model';\n // tslint:disable-next-line:no-unused-variable\nimport { APP_DATE_FORMAT, APP_LOCAL_DATE_FORMAT } from 'app/config/constants';\n\nexport interface IMarcaProps extends StateProps, DispatchProps, RouteComponentProps<{url: string}> {}\n\n\nexport class Marca extends React.Component<IMarcaProps> {\n\n  componentDidMount() {\n    this.props.getEntities();\n  }\n\n\n\n\n\n  render() {\n    const { marcaList, match} = this.props;\n    return (\n      <div>\n        <h2 id=\"marca-heading\">\n          <Translate contentKey=\"concesionarioApp.marca.home.title\">Marcas</Translate>\n          <Link to={`${match.url}/new`} className=\"btn btn-primary float-right jh-create-entity\" id=\"jh-create-entity\">\n            <FontAwesomeIcon icon=\"plus\" />&nbsp;\n            <Translate contentKey=\"concesionarioApp.marca.home.createLabel\">\n              Create new Marca\n            </Translate>\n          </Link>\n        </h2>\n        <div className=\"table-responsive\">\n          <Table responsive>\n            <thead>\n              <tr>\n                <th><Translate contentKey=\"global.field.id\">ID</Translate></th>\n                <th><Translate contentKey=\"concesionarioApp.marca.Nombre\">Nombre</Translate></th>\n                <th><Translate contentKey=\"concesionarioApp.marca.Pais\">Pais</Translate></th>\n                <th />\n              </tr>\n            </thead>\n            <tbody>\n              {\n                marcaList.map((marca, i) => (\n                <tr key={`entity-${i}`}>\n                  <td>\n                    <Button tag={Link} to={`${match.url}/${marca.id}`} color=\"link\" size=\"sm\">\n                      {marca.id}\n                    </Button>\n                  </td>\n                  <td>\n                    {marca.Nombre}\n                  </td>\n                  <td>\n                    {marca.Pais}\n                  </td>\n                    <td className=\"text-right\">\n                      <div className=\"btn-group flex-btn-group-container\">\n                        <Button tag={Link} to={`${match.url}/${marca.id}`} color=\"info\" size=\"sm\">\n                          <FontAwesomeIcon icon=\"eye\" /> <span className=\"d-none d-md-inline\" ><Translate contentKey=\"entity.action.view\">View</Translate></span>\n                        </Button>\n                        <Button tag={Link} to={`${match.url}/${marca.id}/edit`} color=\"primary\" size=\"sm\">\n                          <FontAwesomeIcon icon=\"pencil-alt\" /> <span className=\"d-none d-md-inline\"><Translate contentKey=\"entity.action.edit\">Edit</Translate></span>\n                        </Button>\n                        <Button tag={Link} to={`${match.url}/${marca.id}/delete`} color=\"danger\" size=\"sm\">\n                          <FontAwesomeIcon icon=\"trash\" /> <span className=\"d-none d-md-inline\"><Translate contentKey=\"entity.action.delete\">Delete</Translate></span>\n                        </Button>\n                      </div>\n                    </td>\n                  </tr>\n                ))\n              }\n            </tbody>\n          </Table>\n        </div>\n      </div>\n    );\n  }\n}\n\nconst mapStateToProps = ({ marca }: IRootState) => ({\n  marcaList: marca.entities,\n});\n\nconst mapDispatchToProps = {\n getEntities,\n};\n\ntype StateProps = ReturnType<typeof mapStateToProps>;\ntype DispatchProps = typeof mapDispatchToProps;\n\nexport default connect(mapStateToProps, mapDispatchToProps)(Marca);\n"]}]}